spacebud/__init__.py
spacebud-0.1.0.dist-info/METADATA
spacebud-0.1.0.dist-info/WHEEL
spacebud-0.1.0.dist-info/entry_points.txt
spacebud-0.1.0.dist-info/RECORD
