Metadata-Version: 2.4
Name: spacebud
Version: 0.1.0
Summary: Add your description here
Author-email: Luis Riegger <lri@me.com>
Requires-Python: >=3.13
Requires-Dist: sensitivities>=1.2.0
